setup.cfg
setup.py
financialdata/__init__.py
financialdata/autobindummy.py
financialdata/autodataclean.py
financialdata/automodel.py
financialdata/manudataclean.py
financialdata/manumodel.py
financialdata.egg-info/PKG-INFO
financialdata.egg-info/SOURCES.txt
financialdata.egg-info/dependency_links.txt
financialdata.egg-info/top_level.txt