Metadata-Version: 1.1
Name: financialdata
Version: 0.3
Summary: Final Financial Analytics Project Group H
Home-page: https://github.com/christabelle/financialdata_GroupH
Author: Group-H
Author-email: christabelle@student.ie.edu
License: MIT License
Download-URL: https://github.com/christabelle/financialdata_GroupH/tarball/0.1
Keywords: final,financial,analytics,project
Platform: UNKNOWN
Classifier: Development Status :: 3 - Alpha
Classifier: Intended Audience :: Developers
Classifier: License :: OSI Approved :: MIT License
Classifier: Programming Language :: Python :: 3.5
